<?xml version="1.0" encoding="UTF-8" ?>
<!DOCTYPE mapper PUBLIC "-//mybatis.org//DTD Mapper 3.0//EN" "http://mybatis.org/dtd/mybatis-3-mapper.dtd" >
<mapper namespace="com.mtc.mapper.app.SBLayerFarmSettleMapper" >
  <resultMap id="BaseResultMap" type="com.mtc.entity.app.SBLayerFarmSettle" >
    <!--
      WARNING - @mbggenerated
      This element is automatically generated by MyBatis Generator, do not modify.
    -->
    <id column="id" property="id" jdbcType="INTEGER" />
    <result column="farm_id" property="farmId" jdbcType="INTEGER" />
    <result column="farm_breed_id" property="farmBreedId" jdbcType="INTEGER" />
    <result column="house_id" property="houseId" jdbcType="INTEGER" />
    <result column="settle_month" property="settleMonth" jdbcType="VARCHAR" />
    <result column="fee_type" property="feeType" jdbcType="VARCHAR" />
    <result column="fee_code" property="feeCode" jdbcType="VARCHAR" />
    <result column="fee_name" property="feeName" jdbcType="VARCHAR" />
    <result column="company_code" property="companyCode" jdbcType="VARCHAR" />
    <result column="company_name" property="companyName" jdbcType="VARCHAR" />
    <result column="price_pu" property="pricePu" jdbcType="DECIMAL" />
    <result column="quentity" property="quentity" jdbcType="INTEGER" />
    <result column="weight" property="weight" jdbcType="DECIMAL" />
    <result column="money_sum" property="moneySum" jdbcType="DECIMAL" />
    <result column="bak_var1" property="bakVar1" jdbcType="VARCHAR" />
    <result column="bak_var2" property="bakVar2" jdbcType="VARCHAR" />
    <result column="bak_var3" property="bakVar3" jdbcType="VARCHAR" />
    <result column="bak_num1" property="bakNum1" jdbcType="DECIMAL" />
    <result column="bak_num2" property="bakNum2" jdbcType="DECIMAL" />
    <result column="bak_num3" property="bakNum3" jdbcType="DECIMAL" />
    <result column="bak_num4" property="bakNum4" jdbcType="DECIMAL" />
    <result column="bak_num5" property="bakNum5" jdbcType="DECIMAL" />
    <result column="bak_num6" property="bakNum6" jdbcType="DECIMAL" />
    <result column="create_person" property="createPerson" jdbcType="INTEGER" />
    <result column="create_date" property="createDate" jdbcType="TIMESTAMP" />
    <result column="create_time" property="createTime" jdbcType="TIMESTAMP" />
    <result column="modify_person" property="modifyPerson" jdbcType="INTEGER" />
    <result column="modify_date" property="modifyDate" jdbcType="TIMESTAMP" />
    <result column="modify_time" property="modifyTime" jdbcType="TIMESTAMP" />
  </resultMap>
  <delete id="deleteByPrimaryKey" parameterType="java.lang.Integer" >
    <!--
      WARNING - @mbggenerated
      This element is automatically generated by MyBatis Generator, do not modify.
    -->
    delete from s_b_layer_farm_settle
    where id = #{id,jdbcType=INTEGER}
  </delete>
  <insert id="insert" parameterType="com.mtc.entity.app.SBLayerFarmSettle" >
    <!--
      WARNING - @mbggenerated
      This element is automatically generated by MyBatis Generator, do not modify.
    -->
    <selectKey resultType="java.lang.Integer" keyProperty="id" order="AFTER" >
      SELECT LAST_INSERT_ID()
    </selectKey>
    insert into s_b_layer_farm_settle (farm_id, farm_breed_id, house_id, 
      settle_month, fee_type, fee_code, 
      fee_name, company_code, company_name, 
      price_pu, quentity, weight, 
      money_sum, bak_var1, bak_var2, 
      bak_var3, bak_num1, bak_num2, 
      bak_num3, bak_num4, bak_num5, 
      bak_num6, create_person, create_date, 
      create_time, modify_person, modify_date, 
      modify_time)
    values (#{farmId,jdbcType=INTEGER}, #{farmBreedId,jdbcType=INTEGER}, #{houseId,jdbcType=INTEGER}, 
      #{settleMonth,jdbcType=VARCHAR}, #{feeType,jdbcType=VARCHAR}, #{feeCode,jdbcType=VARCHAR}, 
      #{feeName,jdbcType=VARCHAR}, #{companyCode,jdbcType=VARCHAR}, #{companyName,jdbcType=VARCHAR}, 
      #{pricePu,jdbcType=DECIMAL}, #{quentity,jdbcType=INTEGER}, #{weight,jdbcType=DECIMAL}, 
      #{moneySum,jdbcType=DECIMAL}, #{bakVar1,jdbcType=VARCHAR}, #{bakVar2,jdbcType=VARCHAR}, 
      #{bakVar3,jdbcType=VARCHAR}, #{bakNum1,jdbcType=DECIMAL}, #{bakNum2,jdbcType=DECIMAL}, 
      #{bakNum3,jdbcType=DECIMAL}, #{bakNum4,jdbcType=DECIMAL}, #{bakNum5,jdbcType=DECIMAL}, 
      #{bakNum6,jdbcType=DECIMAL}, #{createPerson,jdbcType=INTEGER}, #{createDate,jdbcType=TIMESTAMP}, 
      #{createTime,jdbcType=TIMESTAMP}, #{modifyPerson,jdbcType=INTEGER}, #{modifyDate,jdbcType=TIMESTAMP}, 
      #{modifyTime,jdbcType=TIMESTAMP})
  </insert>
  <update id="updateByPrimaryKey" parameterType="com.mtc.entity.app.SBLayerFarmSettle" >
    <!--
      WARNING - @mbggenerated
      This element is automatically generated by MyBatis Generator, do not modify.
    -->
    update s_b_layer_farm_settle
    set farm_id = #{farmId,jdbcType=INTEGER},
      farm_breed_id = #{farmBreedId,jdbcType=INTEGER},
      house_id = #{houseId,jdbcType=INTEGER},
      settle_month = #{settleMonth,jdbcType=VARCHAR},
      fee_type = #{feeType,jdbcType=VARCHAR},
      fee_code = #{feeCode,jdbcType=VARCHAR},
      fee_name = #{feeName,jdbcType=VARCHAR},
      company_code = #{companyCode,jdbcType=VARCHAR},
      company_name = #{companyName,jdbcType=VARCHAR},
      price_pu = #{pricePu,jdbcType=DECIMAL},
      quentity = #{quentity,jdbcType=INTEGER},
      weight = #{weight,jdbcType=DECIMAL},
      money_sum = #{moneySum,jdbcType=DECIMAL},
      bak_var1 = #{bakVar1,jdbcType=VARCHAR},
      bak_var2 = #{bakVar2,jdbcType=VARCHAR},
      bak_var3 = #{bakVar3,jdbcType=VARCHAR},
      bak_num1 = #{bakNum1,jdbcType=DECIMAL},
      bak_num2 = #{bakNum2,jdbcType=DECIMAL},
      bak_num3 = #{bakNum3,jdbcType=DECIMAL},
      bak_num4 = #{bakNum4,jdbcType=DECIMAL},
      bak_num5 = #{bakNum5,jdbcType=DECIMAL},
      bak_num6 = #{bakNum6,jdbcType=DECIMAL},
      create_person = #{createPerson,jdbcType=INTEGER},
      create_date = #{createDate,jdbcType=TIMESTAMP},
      create_time = #{createTime,jdbcType=TIMESTAMP},
      modify_person = #{modifyPerson,jdbcType=INTEGER},
      modify_date = #{modifyDate,jdbcType=TIMESTAMP},
      modify_time = #{modifyTime,jdbcType=TIMESTAMP}
    where id = #{id,jdbcType=INTEGER}
  </update>
  <select id="selectByPrimaryKey" resultMap="BaseResultMap" parameterType="java.lang.Integer" >
    <!--
      WARNING - @mbggenerated
      This element is automatically generated by MyBatis Generator, do not modify.
    -->
    select id, farm_id, farm_breed_id, house_id, settle_month, fee_type, fee_code, fee_name, 
    company_code, company_name, price_pu, quentity, weight, money_sum, bak_var1, bak_var2, 
    bak_var3, bak_num1, bak_num2, bak_num3, bak_num4, bak_num5, bak_num6, create_person, 
    create_date, create_time, modify_person, modify_date, modify_time
    from s_b_layer_farm_settle
    where id = #{id,jdbcType=INTEGER}
  </select>
  <select id="selectAll" resultMap="BaseResultMap" >
    <!--
      WARNING - @mbggenerated
      This element is automatically generated by MyBatis Generator, do not modify.
    -->
    select id, farm_id, farm_breed_id, house_id, settle_month, fee_type, fee_code, fee_name, 
    company_code, company_name, price_pu, quentity, weight, money_sum, bak_var1, bak_var2, 
    bak_var3, bak_num1, bak_num2, bak_num3, bak_num4, bak_num5, bak_num6, create_person, 
    create_date, create_time, modify_person, modify_date, modify_time
    from s_b_layer_farm_settle
  </select>
</mapper>